main.py
gsport-2.0.0.dist-info/licenses/LICENSE
src/__init__.py
src/variables.py
src/classes/MyCookie.py
src/classes/__init__.py
src/classes/options.py
src/classes/session.py
src/helpers/__init__.py
src/helpers/downloads.py
src/helpers/eta_readable.py
src/helpers/listings.py
src/helpers/parallel_download.py
src/helpers/print_functions.py
src/helpers/sizeofmetric.py
src/helpers/url.py
src/helpers/usage.py
gsport-2.0.0.dist-info/METADATA
gsport-2.0.0.dist-info/WHEEL
gsport-2.0.0.dist-info/entry_points.txt
gsport-2.0.0.dist-info/top_level.txt
gsport-2.0.0.dist-info/RECORD
