Metadata-Version: 2.4
Name: gsport
Version: 2.0.0
Summary: Download manager for genomscan portal
Author-email: "b.vanwersch" <b.vanwersch@genomescan.nl>, "g.vela" <gonzalov2000@gmail.com>
Project-URL: Homepage, https://github.com/genomescan/gsport
Project-URL: Issues, https://github.com/genomescan/gsport/issues
Classifier: Programming Language :: Python :: 3
Requires-Python: >=3.8
License-File: LICENSE
Requires-Dist: requests==2.32.4
Requires-Dist: terminalcolorpy; python_version >= "3.10"
Dynamic: license-file
